rlrom/__init__.py
rlrom/envs.py
rlrom/plots.py
rlrom/rlrom_run.py
rlrom/testers.py
rlrom/trainers.py
rlrom/utils.py
rlrom/cfgs/Acrobot.yml
rlrom/cfgs/BipedalWalker.yml
rlrom/cfgs/BipedalWalkerHardcore.yml
rlrom/cfgs/CarRacing.yml
rlrom/cfgs/CartPole.yml
rlrom/cfgs/LunarLander.yml
rlrom/cfgs/LunarLanderContinuous.yml
rlrom/cfgs/MountainCar.yml
rlrom/cfgs/MountainCarContinuous.yml
rlrom/cfgs/Pendulum.yml
rlrom/cfgs/highway-env.yml
rlrom/wrappers/reward_machine.py
rlrom/wrappers/stl_wrapper.py
rlrom-0.1.2.dist-info/METADATA
rlrom-0.1.2.dist-info/WHEEL
rlrom-0.1.2.dist-info/entry_points.txt
rlrom-0.1.2.dist-info/licenses/LICENSE
rlrom-0.1.2.dist-info/RECORD
