Metadata-Version: 2.4
Name: rlrom
Version: 0.1.2
Summary: RLROM is a library for testing and training reinforcement learning agent using online monitoring of signal temporal logics formulas, and more.
Author-email: Alexandre Donze <alexandre.donze@univ-grenoble-alpes.fr>
License: BSD-3-Clauses
License-File: LICENSE
Requires-Python: >=3.10
Requires-Dist: bokeh<4.0.0,>=3.6.0
Requires-Dist: gymnasium[classic-control]<2.0.0,>=1.2.0
Requires-Dist: huggingface-hub<0.35.0,>=0.34.4
Requires-Dist: huggingface-sb3<4.0,>=3.0
Requires-Dist: rich<15.0.0,>=14.1.0
Requires-Dist: sb3-contrib<3.0.0,>=2.7.0
Requires-Dist: shimmy<3.0.0,>=2.0.0
Requires-Dist: stable-baselines3<3.0.0,>=2.7.0
Requires-Dist: stlrom<0.3.0,>=0.2.3
Requires-Dist: tensorboard<3.0.0,>=2.20.0
Requires-Dist: tqdm<5.0.0,>=4.67.1
Provides-Extra: highway-env
Requires-Dist: highway-env<2.0.0,>=1.10.1; extra == 'highway-env'
Provides-Extra: old-gym
Requires-Dist: gym<0.27.0,>=0.26.2; extra == 'old-gym'
